qcustomplot_examples_pyside2/__init__.py
qcustomplot_examples_pyside2/all_demos.py
qcustomplot_examples_pyside2/axis-tags.ui
qcustomplot_examples_pyside2/balboa.jpg
qcustomplot_examples_pyside2/heart.svg
qcustomplot_examples_pyside2/mainwindow.ui
qcustomplot_examples_pyside2/q_advancedaxesdemo.py
qcustomplot_examples_pyside2/q_axistags.py
qcustomplot_examples_pyside2/q_barchartdemo.py
qcustomplot_examples_pyside2/q_colormapdemo.py
qcustomplot_examples_pyside2/q_datedemo.py
qcustomplot_examples_pyside2/q_financialdemo.py
qcustomplot_examples_pyside2/q_interactionexample.py
qcustomplot_examples_pyside2/q_itemdemo.py
qcustomplot_examples_pyside2/q_linestyledemo.py
qcustomplot_examples_pyside2/q_logarithmicdemo.py
qcustomplot_examples_pyside2/q_multiaxisdemo.py
qcustomplot_examples_pyside2/q_parametriccurvesdemo.py
qcustomplot_examples_pyside2/q_polarplotdemo.py
qcustomplot_examples_pyside2/q_qcpversion.py
qcustomplot_examples_pyside2/q_quadraticdemo.py
qcustomplot_examples_pyside2/q_realtimedatademo.py
qcustomplot_examples_pyside2/q_scatterpixmapdemo.py
qcustomplot_examples_pyside2/q_scatterstyledemo.py
qcustomplot_examples_pyside2/q_scrollbar_axis_range_control.py
qcustomplot_examples_pyside2/q_simpledemo.py
qcustomplot_examples_pyside2/q_simpleitemdemo.py
qcustomplot_examples_pyside2/q_sincscatterdemo.py
qcustomplot_examples_pyside2/q_statisticaldemo.py
qcustomplot_examples_pyside2/q_styleddemo.py
qcustomplot_examples_pyside2/q_text_document_integration.py
qcustomplot_examples_pyside2/q_textinterface.py
qcustomplot_examples_pyside2/q_texturebrushdemo.py
qcustomplot_examples_pyside2/scrollwindow.ui
qcustomplot_examples_pyside2/solarpanels.jpg
qcustomplot_examples_pyside2/start.bat
qcustomplot_examples_pyside2/start.sh
qcustomplot_examples_pyside2/sun.png
qcustomplot_examples_pyside2/text-document-integration.ui
qcustomplot_pyside2/.gitignore
qcustomplot_pyside2/QCustomPlot.so
qcustomplot_pyside2/__init__.py
qcustomplot_pyside2-2.1.5.dist-info/LICENSE
qcustomplot_pyside2-2.1.5.dist-info/METADATA
qcustomplot_pyside2-2.1.5.dist-info/WHEEL
qcustomplot_pyside2-2.1.5.dist-info/entry_points.txt
qcustomplot_pyside2-2.1.5.dist-info/top_level.txt
qcustomplot_pyside2-2.1.5.dist-info/zip-safe
qcustomplot_pyside2-2.1.5.dist-info/RECORD
