Metadata-Version: 2.1
Name: qcustomplot-pyside2
Version: 2.1.5
Summary: QCustomplot 2.1.0 for Pyside2 5.15.2
Home-page: https://github.com/SBGit-2019/Pyside-QCP
Author: SBC
Author-email: sbc-dev@posteo.de
License: GPLv3+ | Commercial
Keywords: QCP,QCustomPlot,PySide2,Plotting library
Classifier: Development Status :: 5 - Production/Stable
Classifier: Programming Language :: Python :: 3
Classifier: Programming Language :: Python :: 3.6
Classifier: Programming Language :: Python :: 3.7
Classifier: Programming Language :: Python :: 3.8
Classifier: Programming Language :: Python :: 3.9
Classifier: Programming Language :: Python :: 3.10
Classifier: License :: OSI Approved :: GNU General Public License v3 or later (GPLv3+)
Classifier: License :: Other/Proprietary License
Classifier: Operating System :: Microsoft :: Windows
Classifier: Operating System :: POSIX :: Linux
Requires-Python: >=3.6
License-File: LICENSE
Requires-Dist: PySide2 (==5.15.2.1)
Requires-Dist: shiboken2 (==5.15.2.1)
